{"id":"badgeCreations","type":"data","data":{"toggleSideBar":{"created":1739167990707},"toggleExplorer":{"created":1739168185836},"createFile":{"created":1739168200732},"switchFile":{"created":1739168200743},"githubSyncMainWorkspace":{"created":1739168212648},"formatButtons":{"created":1739168395417},"createFolder":{"created":1740577856915},"renameFile":{"created":1740887455772},"renameFolder":{"created":1740887467053},"removeFile":{"created":1741004440305},"moveFile":{"created":1741351741126},"removeFolder":{"created":1742302529676},"toggleNavigationBar":{"created":1744558350454},"toggleSidePreview":{"created":1744558351540},"toggleEditor":{"created":1744558376428},"triggerSync":{"created":1751283618248},"moveFolder":{"created":1751374038625}},"hash":1463205272}